test_vquest/__init__.py
test_vquest/test_util.py
test_vquest/test_vquest.py
vquest/__init__.py
vquest/__main__.py
vquest/config.py
vquest/request.py
vquest/util.py
vquest/version.py
vquest/vq.py
vquest/data/defaults.yml
vquest/data/environment.yml
vquest/data/options.yml
vquest-0.0.10.dist-info/LICENSE
vquest-0.0.10.dist-info/METADATA
vquest-0.0.10.dist-info/WHEEL
vquest-0.0.10.dist-info/entry_points.txt
vquest-0.0.10.dist-info/top_level.txt
vquest-0.0.10.dist-info/RECORD
