Metadata-Version: 2.1
Name: vquest
Version: 0.0.10
Summary: Automate IMGT V-QUEST usage on imgt.org
Home-page: https://github.com/shawhahnlab/vquest
Author: Jesse Connell
Author-email: jesse@ressy.us
Classifier: Programming Language :: Python :: 3
Classifier: License :: OSI Approved :: GNU Affero General Public License v3
Classifier: Operating System :: OS Independent
Requires-Python: >=3.6
License-File: LICENSE
Requires-Dist: biopython
Requires-Dist: PyYAML
Requires-Dist: requests
Requires-Dist: requests-html
